[
    {
        "Codigo":  "99",
        "Id":  1,
        "Apellido":  "Ltda",
        "Visible":  0,
        "Activo":  0,
        "Historico":  -1,
        "Cargo":  "Master",
        "Oculto":  -1,
        "Password":  "9876",
        "Usuario":  "SG",
        "Deshacer":  -1,
        "Acceso":  1,
        "Nombre":  "Sistemas y Bingos",
        "ResumenRinde":  "12345"
    },
    {
        "Codigo":  "98",
        "Id":  2,
        "Apellido":  "Ltda",
        "Visible":  -1,
        "Activo":  -1,
        "Historico":  0,
        "Cargo":  "Master",
        "Oculto":  -1,
        "Password":  "1475",
        "Usuario":  "FC",
        "Deshacer":  -1,
        "Acceso":  2,
        "Nombre":  "A",
        "ResumenRinde":  "3154"
    }
]
